testpysecure/__init__.py
testpysecure-1.1.1.dist-info/METADATA
testpysecure-1.1.1.dist-info/WHEEL
testpysecure-1.1.1.dist-info/top_level.txt
testpysecure-1.1.1.dist-info/RECORD
