Metadata-Version: 2.2
Name: testpysecure
Version: 1.1.1
Summary: Malicious package for dependency confusion attack
Author: Attacker Name
Author-email: attacker@example.com
Requires-Dist: requests
Dynamic: author
Dynamic: author-email
Dynamic: requires-dist
Dynamic: summary
